meetlify/__init__.py
meetlify/api.py
meetlify/categories.py
meetlify/cli.py
meetlify/configs.py
meetlify/constants.py
meetlify/meetups.py
meetlify/pages.py
meetlify/posts.py
meetlify/redirects.py
meetlify/robots.py
meetlify/sitemaps.py
meetlify/utils.py
meetlify/share/__init__.py
meetlify/share/configs.json
meetlify/share/robots.txt
meetlify/share/content/images/fatureimage.png
meetlify/share/content/meetups/0001.md
meetlify/share/content/meetups/0002.md
meetlify/share/content/meetups/0003.md
meetlify/share/content/pages/contact.md
meetlify/share/content/pages/home.md
meetlify/share/content/pages/privacy.md
meetlify/share/content/pages/terms.md
meetlify/themes/lindau/static/assets/about.png
meetlify/themes/lindau/static/assets/author.png
meetlify/themes/lindau/static/assets/banner.png
meetlify/themes/lindau/static/assets/favicon.png
meetlify/themes/lindau/static/assets/logo.png
meetlify/themes/lindau/static/css/bootstrap-grid.css
meetlify/themes/lindau/static/css/bootstrap-grid.css.map
meetlify/themes/lindau/static/css/bootstrap-grid.min.css
meetlify/themes/lindau/static/css/bootstrap-grid.min.css.map
meetlify/themes/lindau/static/css/bootstrap-grid.rtl.css
meetlify/themes/lindau/static/css/bootstrap-grid.rtl.css.map
meetlify/themes/lindau/static/css/bootstrap-grid.rtl.min.css
meetlify/themes/lindau/static/css/bootstrap-grid.rtl.min.css.map
meetlify/themes/lindau/static/css/bootstrap-icons.css
meetlify/themes/lindau/static/css/bootstrap-reboot.css
meetlify/themes/lindau/static/css/bootstrap-reboot.css.map
meetlify/themes/lindau/static/css/bootstrap-reboot.min.css
meetlify/themes/lindau/static/css/bootstrap-reboot.min.css.map
meetlify/themes/lindau/static/css/bootstrap-reboot.rtl.css
meetlify/themes/lindau/static/css/bootstrap-reboot.rtl.css.map
meetlify/themes/lindau/static/css/bootstrap-reboot.rtl.min.css
meetlify/themes/lindau/static/css/bootstrap-reboot.rtl.min.css.map
meetlify/themes/lindau/static/css/bootstrap-utilities.css
meetlify-0.1.12.dist-info/LICENSE
meetlify-0.1.12.dist-info/METADATA
meetlify-0.1.12.dist-info/WHEEL
meetlify-0.1.12.dist-info/entry_points.txt
meetlify-0.1.12.dist-info/top_level.txt
meetlify-0.1.12.dist-info/RECORD
